{
   "pluginmetadataversion": 2,
   "name": "Delphi VMT Analyzer",
   "author": "ImNotAVirus",
   "type": [
      "helper"
   ],
   "api": [
      "python3"
   ],
   "description": "Find Delphi VMTs and generate their structures",
   "longdescription": "# Delphi VMT Analyzer (v0.1.1)\nAuthor: **ImNotAVirus**\n\n_Find Delphi VMTs and generate their structures_\n\n## Description:\n\nThis plugin is intended to facilitate the revese engineering of binaries written in Delphi.\n\nFor that, it:\n\n- Finds the Virtual Method Table (VMT) of Delphi classes\n- Creates a structure for each VMT (class name, instance size, virtual methods, etc...)\n- Creates a tag for each VMT in order to locate them more easily\n\n**Warning**: This plugin currently only supports 32bits PE (Portable Executable). For more details on upcoming features, you can refer to [TODO.md](./TODO.md).\n\n![example](./assets/example.png)\n\n## Installation Instructions\n\n### Darwin\n\nNo special instructions, package manager is recommended\n\n### Windows\n\nNo special instructions, package manager is recommended\n\n### Linux\n\nNo special instructions, package manager is recommended\n\n## Examples\n\nThis repo contains different examples to show how the plugin works in scripting mode.  \nYou can view them [here](./examples).\n\n**Warning**: although DelphiNinja does not require dependencies, some examples may require dependencies.  \nFor more information, please refer to this [page](./examples/README.md).\n\n## Minimum Version\n\nThis plugin has been tested with the following minimum version of Binary Ninja:\n\n* release: N/A\n* dev: 2440\n\n## License\n\nThis plugin is released under a MIT license.",
   "license": {
      "name": "MIT",
      "text": "Copyright 2020 ImNotAVirus\n\nPermission is hereby granted, free of charge, to any person obtaining a copy of this software and associated documentation files (the \"Software\"), to deal in the Software without restriction, including without limitation the rights to use, copy, modify, merge, publish, distribute, sublicense, and/or sell copies of the Software, and to permit persons to whom the Software is furnished to do so, subject to the following conditions:\n\nThe above copyright notice and this permission notice shall be included in all copies or substantial portions of the Software.\n\nTHE SOFTWARE IS PROVIDED \"AS IS\", WITHOUT WARRANTY OF ANY KIND, EXPRESS OR IMPLIED, INCLUDING BUT NOT LIMITED TO THE WARRANTIES OF MERCHANTABILITY, FITNESS FOR A PARTICULAR PURPOSE AND NONINFRINGEMENT. IN NO EVENT SHALL THE AUTHORS OR COPYRIGHT HOLDERS BE LIABLE FOR ANY CLAIM, DAMAGES OR OTHER LIABILITY, WHETHER IN AN ACTION OF CONTRACT, TORT OR OTHERWISE, ARISING FROM, OUT OF OR IN CONNECTION WITH THE SOFTWARE OR THE USE OR OTHER DEALINGS IN THE SOFTWARE."
   },
   "platforms": [
      "Darwin",
      "Windows",
      "Linux"
   ],
   "installinstructions": {
      "Darwin": "No special instructions, package manager is recommended",
      "Windows": "No special instructions, package manager is recommended",
      "Linux": "No special instructions, package manager is recommended"
   },
   "version": "0.1.1",
   "minimumbinaryninjaversion": 2440
}
